Products.ExternalMethod-6.0-py3.11-nspkg.pth
Products/ExternalMethod/ExternalMethod.py
Products/ExternalMethod/__init__.py
Products/ExternalMethod/extmethod.gif
Products/ExternalMethod/dtml/methodAdd.dtml
Products/ExternalMethod/dtml/methodEdit.dtml
Products/ExternalMethod/tests/__init__.py
Products/ExternalMethod/tests/testExternalMethod.py
Products/ExternalMethod/tests/Extensions/Test.py
Products/ExternalMethod/www/function.gif
Products.ExternalMethod-6.0.dist-info/LICENSE.txt
Products.ExternalMethod-6.0.dist-info/METADATA
Products.ExternalMethod-6.0.dist-info/WHEEL
Products.ExternalMethod-6.0.dist-info/namespace_packages.txt
Products.ExternalMethod-6.0.dist-info/top_level.txt
Products.ExternalMethod-6.0.dist-info/RECORD
